lemay_hire_me/__init__.py
lemay_hire_me/main.py
lemay_hire_me/schemas/__init__.py
lemay_hire_me/schemas/poll.py
lemay_hire_me/utils/__init__.py
lemay_hire_me/utils/api.py
lemay_hire_me/utils/config/__init__.py
lemay_hire_me/utils/config/config.py
lemay_hire_me/utils/config.py
lemay_hire_me/utils/const.py
lemay_hire_me/utils/db/__init__.py
lemay_hire_me/utils/db/jsondb.py
lemay_hire_me/utils/depend_files.py
lemay_hire_me/utils/styled_text.py
lemay_hire_me/validators/__init__.py
lemay_hire_me/validators/email.py
lemay_hire_me/validators/empty.py
lemay_hire_me/validators/user_input.py
lemay_hire_me/validators/weblinks.py
lemay_hire_me-0.1.0.dist-info/entry_points.txt
lemay_hire_me-0.1.0.dist-info/WHEEL
lemay_hire_me-0.1.0.dist-info/METADATA
lemay_hire_me-0.1.0.dist-info/RECORD
