Metadata-Version: 2.1
Name: lemay-hire-me
Version: 0.1.0
Summary: 
Author: Alexey Belochenko
Author-email: alexey@lemay.ai
Requires-Python: >=3.9,<4.0
Classifier: Programming Language :: Python :: 3
Classifier: Programming Language :: Python :: 3.10
Classifier: Programming Language :: Python :: 3.9
Requires-Dist: GitPython (>=3.1.31,<4.0.0)
Requires-Dist: PyInquirer (>=1.0.3,<2.0.0)
Requires-Dist: pydantic (>=1.10.5,<2.0.0)
Requires-Dist: pyfiglet (>=0.8.post1,<0.9)
Requires-Dist: requests (>=2.28.2,<3.0.0)
Requires-Dist: termcolor (>=2.2.0,<3.0.0)
Requires-Dist: typer[all] (>=0.7.0,<0.8.0)
